mxop/__init__.py
mxop/gluon/__init__.py
mxop/gluon/count_hooks.py
mxop/gluon/utils.py
mxop-0.2.0.dist-info/LICENSE
mxop-0.2.0.dist-info/METADATA
mxop-0.2.0.dist-info/WHEEL
mxop-0.2.0.dist-info/top_level.txt
mxop-0.2.0.dist-info/zip-safe
mxop-0.2.0.dist-info/RECORD
