Metadata-Version: 2.1
Name: mxop
Version: 0.2.0
Summary: A tool to count OPs and paramters of MXNet model.
Home-page: https://github.com/hey-yahei/OpSummary.MXNet
Author: YaHei
Author-email: hey-yahei@qq.com
License: MIT
Platform: UNKNOWN
Classifier: Programming Language :: Python :: 3
Requires-Dist: mxnet
